{
  "minecraft:recipes/misc/iron_ingot_from_iron_block": {
    "criteria": {
      "has_iron_block": "2022-07-16 17:07:06 +0000"
    },
    "done": true
  },
  "minecraft:recipes/redstone/redstone": {
    "criteria": {
      "has_redstone_block": "2022-07-16 17:07:07 +0000"
    },
    "done": true
  },
  "minecraft:recipes/tools/clock": {
    "criteria": {
      "has_redstone": "2022-07-16 17:07:08 +0000"
    },
    "done": true
  },
  "minecraft:recipes/redstone/redstone_torch": {
    "criteria": {
      "has_redstone": "2022-07-16 17:07:08 +0000"
    },
    "done": true
  },
  "minecraft:recipes/decorations/chest": {
    "criteria": {
      "has_lots_of_items": "2022-07-16 17:07:05 +0000"
    },
    "done": true
  },
  "minecraft:recipes/tools/compass": {
    "criteria": {
      "has_redstone": "2022-07-16 17:07:08 +0000"
    },
    "done": true
  },
  "minecraft:recipes/redstone/note_block": {
    "criteria": {
      "has_redstone": "2022-07-16 17:07:08 +0000"
    },
    "done": true
  },
  "minecraft:recipes/redstone/dropper": {
    "criteria": {
      "has_redstone": "2022-07-16 17:07:08 +0000"
    },
    "done": true
  },
  "minecraft:recipes/redstone/redstone_block": {
    "criteria": {
      "has_redstone": "2022-07-16 17:07:08 +0000"
    },
    "done": true
  },
  "minecraft:recipes/decorations/anvil": {
    "criteria": {
      "has_iron_block": "2022-07-16 17:07:06 +0000"
    },
    "done": true
  },
  "minecraft:recipes/redstone/piston": {
    "criteria": {
      "has_redstone": "2022-07-16 17:07:08 +0000"
    },
    "done": true
  },
  "minecraft:recipes/redstone/target": {
    "criteria": {
      "has_redstone": "2022-07-16 17:07:08 +0000"
    },
    "done": true
  },
  "minecraft:adventure/adventuring_time": {
    "criteria": {
      "minecraft:desert": "2022-07-16 17:05:09 +0000",
      "minecraft:plains": "2022-07-16 17:06:31 +0000"
    },
    "done": false
  },
  "DataVersion": 3105
}